fastvector/__init__.py
fastvector/vector.py
fastvector/version.py
cnxfastvector-0.2.0.dist-info/LICENSE
cnxfastvector-0.2.0.dist-info/METADATA
cnxfastvector-0.2.0.dist-info/WHEEL
cnxfastvector-0.2.0.dist-info/top_level.txt
cnxfastvector-0.2.0.dist-info/RECORD
