Metadata-Version: 2.1
Name: cnxfastvector
Version: 0.2.0
Summary: short package description
Author-email: author <author@example.com>
License: MIT
Project-URL: Homepage, https://github.com/pypa/sampleproject
Project-URL: Bug Tracker, https://github.com/pypa/sampleproject/issues
Classifier: License :: OSI Approved :: MIT License
Classifier: Operating System :: OS Independent
Classifier: Programming Language :: Python :: 3
Requires-Python: >=3.7
License-File: LICENSE
Requires-Dist: numpy (==1.21.5)
Provides-Extra: testing
Requires-Dist: autopep8 ; extra == 'testing'
Requires-Dist: black ; extra == 'testing'
Requires-Dist: codecov ; extra == 'testing'
Requires-Dist: flake8 ; extra == 'testing'
Requires-Dist: isort ; extra == 'testing'
Requires-Dist: mypy ; extra == 'testing'
Requires-Dist: pre-commit ; extra == 'testing'
Requires-Dist: pylint ; extra == 'testing'
Requires-Dist: pytest ; extra == 'testing'
Requires-Dist: pytest-cov ; extra == 'testing'
Requires-Dist: tox ; extra == 'testing'
